{
    "curWeek": "2.15.2025 - 2.21.2025",
    "items": [
        {
            "name": "晨兴圣言",
            "book": "2025年秋季长老负责弟兄训练 马太福音五至七章极重要的方面",
            "chapter": "第六周",
            "subject": "要完全，像我们的天父完全一样",
            "link": "https://my-google-api-server.onrender.com/study/"
        },
        {
            "name": "圣经",
            "books": [
                {
                    "name": "旧约", 
                    "books": [
                        {
                        "name": "列王纪上",
                        "chapters": "第3~7章"
                        }
                    ]
                },
                {
                    "name": "新约", 
                    "books": [
                        {
                        "name": " 马可福音",
                        "chapters": "第5~9章"
                        }
                    ]
                }
            ],
            "link": "https://my-google-api-server.onrender.com/study/"
        },
        {
            "name": "属灵书报",
            "books": [
                {
                    "name": "生命的经历", 
                    "chapters": "第四篇-对付罪, 第五篇-对付的世界"
                }
            ],
            "date": "3.12.2025",
            "link": "https://my-google-api-server.onrender.com/study/"
        }
    ]
}